djmessenger/__init__.py
djmessenger/admin.py
djmessenger/apps.py
djmessenger/exceptions.py
djmessenger/facebook_locales.py
djmessenger/filtering.py
djmessenger/handling.py
djmessenger/models.py
djmessenger/payload.py
djmessenger/receiving.py
djmessenger/replying.py
djmessenger/routing.py
djmessenger/settings.py
djmessenger/urls.py
djmessenger/views.py
djmessenger/management/__init__.py
djmessenger/management/commands/__init__.py
djmessenger/management/commands/configure_get_started_button.py
djmessenger/management/commands/configure_greetings.py
djmessenger/management/commands/configure_persistent_menu.py
djmessenger/management/commands/get_random_endpoint.py
djmessenger/migrations/0001_initial.py
djmessenger/migrations/0002_callback_fbuserprofile_getstartedbutton_persistentmenu.py
djmessenger/migrations/0003_userlocation.py
djmessenger/migrations/0004_auto_20160823_2245.py
djmessenger/migrations/0005_auto_20160823_2249.py
djmessenger/migrations/0006_auto_20160823_2337.py
djmessenger/migrations/0007_auto_20160823_2348.py
djmessenger/migrations/0008_auto_20160824_0519.py
djmessenger/migrations/0009_auto_20160824_0625.py
djmessenger/migrations/0010_auto_20160824_0649.py
djmessenger/migrations/0011_sending.py
djmessenger/migrations/0012_auto_20160825_0718.py
djmessenger/migrations/0013_auto_20160829_0510.py
djmessenger/migrations/0014_auto_20161110_1856.py
djmessenger/migrations/__init__.py
djmessenger/tests/__init__.py
djmessenger/tests/test_i18n.py
djmessenger/tests/test_loggable.py
djmessenger/tests/test_models.py
djmessenger/tests/test_receiving.py
djmessenger/tests/test_routing.py
djmessenger/tests/test_serializable.py
djmessenger/utils/__init__.py
djmessenger/utils/decorators.py
djmessenger/utils/default_routing_policy.py
djmessenger/utils/filelock.py
djmessenger/utils/geocoding.py
djmessenger/utils/serializable.py
djmessenger/utils/utils.py
djmessenger-1.1.11.dist-info/DESCRIPTION.rst
djmessenger-1.1.11.dist-info/METADATA
djmessenger-1.1.11.dist-info/RECORD
djmessenger-1.1.11.dist-info/WHEEL
djmessenger-1.1.11.dist-info/metadata.json
djmessenger-1.1.11.dist-info/top_level.txt
