Metadata-Version: 2.0
Name: djmessenger
Version: 1.1.11
Summary: A simple framework to create powerful Facebook Messenger BOT
Home-page: https://github.com/ifanchu/djmessenger
Author: Evan Chu
Author-email: ifanchu@ifanchu.com
License: GNU GENERAL PUBLIC LICENSE Version 2
Keywords: facebook messenger bot
Platform: UNKNOWN
Classifier: Development Status :: 3 - Alpha
Classifier: Intended Audience :: Developers
Classifier: Topic :: Software Development :: Libraries :: Python Modules
Classifier: License :: OSI Approved :: GNU General Public License v2 (GPLv2)
Classifier: Programming Language :: Python :: 3.4
Requires-Dist: django (>=1.9.8)
Requires-Dist: djangorestframework (>=3.4.5)
Requires-Dist: requests (>=2.11.1)
Requires-Dist: xmltodict (>=0.10.2)
